tdengine_mcp_server/.env.example
tdengine_mcp_server/__init__.py
tdengine_mcp_server/__main__.py
tdengine_mcp_server/prompt.md
tdengine_mcp_server/py.typed
tdengine_mcp_server/server.py
tdengine_mcp_server/template.py
tdengine_mcp_server-0.1.0.dist-info/METADATA
tdengine_mcp_server-0.1.0.dist-info/WHEEL
tdengine_mcp_server-0.1.0.dist-info/licenses/LICENSE
tdengine_mcp_server-0.1.0.dist-info/RECORD
