Metadata-Version: 2.4
Name: tdengine-mcp-server
Version: 0.1.0
Summary: Add your description here
Author-email: lcprunstone@163.com
License-File: LICENSE
Requires-Python: >=3.12
Requires-Dist: jinja2
Requires-Dist: mcp[cli]
Requires-Dist: taospy
